{
  "age_buckets": [
    "0-4",
    "5-9",
    "10-14",
    "15-19",
    "20-24",
    "25-29",
    "30-34",
    "35-39",
    "40-44",
    "45-49",
    "50-54",
    "55-59",
    "60-64",
    "65-69",
    "70-74",
    "75-79",
    "80-84",
    "85-89",
    "90-94",
    "95-99",
    "100+"
  ],
  "age_bucket_starts": [
    0,
    5,
    10,
    15,
    20,
    25,
    30,
    35,
    40,
    45,
    50,
    55,
    60,
    65,
    70,
    75,
    80,
    85,
    90,
    95,
    100
  ],
  "bucket_size": 5,
  "eto_classes": [
    "0",
    "1",
    "2",
    "3",
    "5",
    "6",
    "7",
    "8",
    "9"
  ],
  "eto_labels": {
    "0": "Általános művek",
    "1": "Filozófia. Pszichológia",
    "2": "Vallás. Teológia",
    "3": "Társadalomtudományok",
    "5": "Matematika. Természettudományok",
    "6": "Alkalmazott tudományok. Orvostudomány. Műszaki tudományok",
    "7": "Művészetek. Szórakozás. Sport",
    "8": "Nyelv és irodalom",
    "9": "Régészet. Földrajz. Életrajz. Történelem"
  },
  "matrix": [
    [
      218,
      0,
      0,
      4,
      18,
      18,
      1,
      121,
      2
    ],
    [
      176,
      1,
      1,
      19,
      48,
      74,
      8,
      507,
      12
    ],
    [
      85,
      45,
      5,
      125,
      37,
      158,
      56,
      811,
      29
    ],
    [
      21,
      23,
      1,
      25,
      16,
      49,
      6,
      432,
      8
    ],
    [
      14,
      31,
      2,
      83,
      5,
      75,
      14,
      363,
      18
    ],
    [
      5,
      10,
      0,
      42,
      14,
      33,
      8,
      212,
      10
    ],
    [
      26,
      22,
      0,
      66,
      10,
      60,
      16,
      349,
      11
    ],
    [
      28,
      35,
      4,
      114,
      23,
      51,
      21,
      352,
      31
    ],
    [
      51,
      56,
      5,
      72,
      21,
      77,
      48,
      821,
      30
    ],
    [
      21,
      28,
      7,
      54,
      11,
      94,
      31,
      632,
      11
    ],
    [
      0,
      11,
      3,
      33,
      2,
      44,
      16,
      655,
      18
    ],
    [
      10,
      25,
      5,
      40,
      24,
      51,
      16,
      1036,
      14
    ],
    [
      12,
      5,
      3,
      26,
      19,
      36,
      13,
      907,
      10
    ],
    [
      25,
      44,
      11,
      86,
      26,
      59,
      37,
      1535,
      47
    ],
    [
      5,
      38,
      8,
      50,
      15,
      38,
      23,
      2304,
      30
    ],
    [
      9,
      18,
      1,
      74,
      1,
      43,
      35,
      1026,
      27
    ],
    [
      5,
      0,
      1,
      13,
      7,
      3,
      11,
      394,
      9
    ],
    [
      0,
      0,
      1,
      4,
      2,
      1,
      0,
      90,
      6
    ],
    [
      0,
      0,
      0,
      4,
      0,
      0,
      0,
      133,
      1
    ],
    [
      0,
      0,
      0,
      0,
      0,
      0,
      0,
      0,
      0
    ],
    [
      0,
      0,
      0,
      0,
      0,
      0,
      0,
      0,
      0
    ]
  ],
  "max": 2304
}